swissweather/AbstractAuth.py
swissweather/Auth.py
swissweather/TokenManager.py
swissweather/__init__.py
swissweather/api.py
swissweather-0.2.4.dist-info/LICENSE
swissweather-0.2.4.dist-info/METADATA
swissweather-0.2.4.dist-info/WHEEL
swissweather-0.2.4.dist-info/top_level.txt
swissweather-0.2.4.dist-info/RECORD
