Metadata-Version: 2.1
Name: swissweather
Version: 0.2.4
Summary: SRF Meteo weather forecast in Switzerland
Home-page: https://github.com/davosian/swissweather
Author: Dennis Staiger
Author-email: dnsstaiger@gmx.net
License: UNKNOWN
Platform: UNKNOWN
Classifier: Programming Language :: Python :: 3
Classifier: License :: OSI Approved :: MIT License
Classifier: Operating System :: OS Independent
Classifier: Topic :: Home Automation
Classifier: Topic :: Software Development :: Libraries :: Python Modules
Requires-Python: >=3.8
Requires-Dist: requests
Requires-Dist: oauthlib
Requires-Dist: requests-oauthlib
Requires-Dist: aiohttp
